convalidtor/__init__.py
convalidtor/src/__init__.py
convalidtor/src/validator.py
convalidatorx-0.1.5.dist-info/METADATA
convalidatorx-0.1.5.dist-info/WHEEL
convalidatorx-0.1.5.dist-info/top_level.txt
convalidatorx-0.1.5.dist-info/RECORD
