Metadata-Version: 2.1
Name: convalidatorx
Version: 0.1.5
Summary: validation
Author: nxbz44
Author-email: nxbz44@yopmail.com
Requires-Dist: requests
